notion/__init__.py
notion/api.py
notion_sdk_py-0.0.1.dist-info/LICENSE
notion_sdk_py-0.0.1.dist-info/METADATA
notion_sdk_py-0.0.1.dist-info/WHEEL
notion_sdk_py-0.0.1.dist-info/top_level.txt
notion_sdk_py-0.0.1.dist-info/RECORD
