Metadata-Version: 2.1
Name: notion-sdk-py
Version: 0.0.1
Summary: A simple and easy to use client for the Notion API for python
Home-page: https://github.com/blue-hope/notion-sdk-py
Author: blue-hope
Author-email: ms7045436@gmail.com
License: MIT
Keywords: notion,notion-client,notion-api,notion-lib
Platform: UNKNOWN
Classifier: Development Status :: 3 - Alpha
Classifier: Intended Audience :: Developers
Classifier: License :: OSI Approved :: MIT License
Classifier: Operating System :: OS Independent
Classifier: Programming Language :: Python :: 3
Classifier: Programming Language :: Python :: 3.7
Classifier: Programming Language :: Python :: 3.8
Classifier: Programming Language :: Python :: 3.9
Requires-Dist: certifi (==2020.12.5)
Requires-Dist: chardet (==4.0.0)
Requires-Dist: idna (==2.10)
Requires-Dist: requests (==2.25.1)
Requires-Dist: urllib3 (==1.26.4)
